Workbook

Sheet Sheet1
A1: Order ID | B1: Order Date | C1: Region | D1: Product | E1: Quantity | F1: Unit Price | G1: Unit Cost | H1: Revenue | I1: Profit
A2: ORD001 | B2: 46023 | C2: South | D2: Laptop Stand | E2: 3 | F2: 1200 | G2: 700 | H2: =E2*F2 -> 3600 | I2: =E2*(F2-G2) -> 1500
A3: ORD002 | B3: 46027 | C3: North | D3: Wireless Mouse | E3: 5 | F3: 500 | G3: 250 | H3: =E3*F3 -> 2500 | I3: =E3*(F3-G3) -> 1250
A4: ORD003 | B4: 46032 | C4: East | D4: Keyboard | E4: 2 | F4: 1500 | G4: 900 | H4: =E4*F4 -> 3000 | I4: =E4*(F4-G4) -> 1200
A5: ORD004 | B5: 46037 | C5: West | D5: USB-C Hub | E5: 4 | F5: 1800 | G5: 1100 | H5: =E5*F5 -> 7200 | I5: =E5*(F5-G5) -> 2800
A6: ORD005 | B6: 46042 | C6: South | D6: Webcam | E6: 2 | F6: 2500 | G6: 1600 | H6: =E6*F6 -> 5000 | I6: =E6*(F6-G6) -> 1800
A7: ORD006 | B7: 46047 | C7: North | D7: Headset | E7: 3 | F7: 2000 | G7: 1200 | H7: =E7*F7 -> 6000 | I7: =E7*(F7-G7) -> 2400
A8: ORD007 | B8: 46052 | C8: East | D8: Laptop Stand | E8: 5 | F8: 1200 | G8: 700 | H8: =E8*F8 -> 6000 | I8: =E8*(F8-G8) -> 2500
A9: ORD008 | B9: 46057 | C9: West | D9: Wireless Mouse | E9: 8 | F9: 500 | G9: 250 | H9: =E9*F9 -> 4000 | I9: =E9*(F9-G9) -> 2000
A10: ORD009 | B10: 46062 | C10: South | D10: Keyboard | E10: 3 | F10: 1500 | G10: 900 | H10: =E10*F10 -> 4500 | I10: =E10*(F10-G10) -> 1800
A11: ORD010 | B11: 46067 | C11: North | D11: USB-C Hub | E11: 2 | F11: 1800 | G11: 1100 | H11: =E11*F11 -> 3600 | I11: =E11*(F11-G11) -> 1400
A12: ORD011 | B12: 46072 | C12: East | D12: Webcam | E12: 4 | F12: 2500 | G12: 1600 | H12: =E12*F12 -> 10000 | I12: =E12*(F12-G12) -> 3600
A13: ORD012 | B13: 46077 | C13: West | D13: Headset | E13: 5 | F13: 2000 | G13: 1200 | H13: =E13*F13 -> 10000 | I13: =E13*(F13-G13) -> 4000

Sheet Dashboard
A1: ORQENVO TECHNOLOGIES | SALES ANALYTICS
A2: Simple Ideas. Smarter Technology.
A3: Metric | B3: Value
A4: Total Revenue | B4: =SUM(Sheet1!H2:H13) -> 65400
A5: Total Profit | B5: =SUM(Sheet1!I2:I13) -> 26250
A6: Total Orders | B6: =COUNTA(Sheet1!A2:A13) -> 12
A7: Total Quantity Sold | B7: =SUM(Sheet1!E2:E13) -> 46
A10: Product | B10: Revenue | D10: Product | E10: Profit
A11: Laptop Stand | B11: =SUMIF(Sheet1!$D$2:$D$13,A11,Sheet1!$H$2:$H$13) -> 9600 | D11: Laptop Stand | E11: =SUMIF(Sheet1!$D$2:$D$13,D11,Sheet1!$I$2:$I$13) -> 4000
A12: Wireless Mouse | B12: =SUMIF(Sheet1!$D$2:$D$13,A12,Sheet1!$H$2:$H$13) -> 6500 | D12: Wireless Mouse | E12: =SUMIF(Sheet1!$D$2:$D$13,D12,Sheet1!$I$2:$I$13) -> 3250
A13: Keyboard | B13: =SUMIF(Sheet1!$D$2:$D$13,A13,Sheet1!$H$2:$H$13) -> 7500 | D13: Keyboard | E13: =SUMIF(Sheet1!$D$2:$D$13,D13,Sheet1!$I$2:$I$13) -> 3000
A14: USB-C Hub | B14: =SUMIF(Sheet1!$D$2:$D$13,A14,Sheet1!$H$2:$H$13) -> 10800 | D14: USB-C Hub | E14: =SUMIF(Sheet1!$D$2:$D$13,D14,Sheet1!$I$2:$I$13) -> 4200
A15: Webcam | B15: =SUMIF(Sheet1!$D$2:$D$13,A15,Sheet1!$H$2:$H$13) -> 15000 | D15: Webcam | E15: =SUMIF(Sheet1!$D$2:$D$13,D15,Sheet1!$I$2:$I$13) -> 5400
A16: Headset | B16: =SUMIF(Sheet1!$D$2:$D$13,A16,Sheet1!$H$2:$H$13) -> 16000 | D16: Headset | E16: =SUMIF(Sheet1!$D$2:$D$13,D16,Sheet1!$I$2:$I$13) -> 6400
A18: Demo dataset for portfolio practice. Revenue = Quantity × Unit Price; Profit = Quantity × (Unit Price − Unit Cost).
